Metadata-Version: 2.1
Name: brother_ql-inventree
Version: 1.3
Summary: Python package to talk to Brother QL label printers
Home-page: https://github.com/matmair/brother_ql-inventree
Author: Philipp Klaus
Author-email: Philipp Klaus <philipp.l.klaus@web.de>, Matthias Mair <code@mjmair.com>
License: GPL
Project-URL: repository, https://github.com/matmair/brother_ql-inventree
Keywords: Brother,QL-500,QL-550,QL-560,QL-570,QL-600,QL-700,QL-710W,QL-720NW,QL-800,QL-810W,QL-820NWB,QL-1050,QL-1060N,QL-1100,QL-1110NWB,QL-1115NWB
Platform: any
Classifier: Development Status :: 4 - Beta
Classifier: Operating System :: OS Independent
Classifier: License :: OSI Approved :: GNU General Public License v3 or later (GPLv3+)
Classifier: Programming Language :: Python
Classifier: Programming Language :: Python :: 3
Classifier: Topic :: Scientific/Engineering :: Visualization
Classifier: Topic :: System :: Hardware :: Hardware Drivers
License-File: LICENSE
Requires-Dist: click
Requires-Dist: packbits
Requires-Dist: pillow >=10.0.0
Requires-Dist: pyusb
Requires-Dist: attrs
Requires-Dist: enum34 ; python_version < "3.4"
Requires-Dist: typing ; python_version < "3.5"
